pango_aliasor/__init__.py
pango_aliasor/aliasor.py
pango_aliasor-0.3.0.dist-info/LICENSE
pango_aliasor-0.3.0.dist-info/METADATA
pango_aliasor-0.3.0.dist-info/WHEEL
pango_aliasor-0.3.0.dist-info/top_level.txt
pango_aliasor-0.3.0.dist-info/RECORD
