Metadata-Version: 2.1
Name: pango-aliasor
Version: 0.3.0
Summary: Pango lineage aliasing and dealiasing
Home-page: https://github.com/corneliusroemer/pango_aliasor
Author: Cornelius Roemer
Author-email: cornelius.roemer@gmail.com
License: : OSI Approved :: MIT License
Classifier: License :: OSI Approved :: MIT License
Classifier: Programming Language :: Python :: 3
Classifier: Programming Language :: Python :: 3 :: Only
Classifier: Programming Language :: Python :: 3.7
Classifier: Programming Language :: Python :: 3.8
Classifier: Programming Language :: Python :: 3.9
Classifier: Programming Language :: Python :: 3.10
Classifier: Programming Language :: Python :: 3.11
Requires-Python: >=3.7
License-File: LICENSE
